{
    "timestamp": "20260404_152439",
    "problem": "zurich_25_6",
    "problem_size": 25,
    "type": "TSP",
    "comment": "TSP instance with 25 nodes. City: Zurich, Switzerland, Seed: 48",
    "solver": "UTSPNeuralSolver",
    "time_to_solve": 17.062634323956445,
    "cost": 15427.0,
    "tour": [
        0,
        23,
        22,
        11,
        12,
        8,
        9,
        17,
        18,
        21,
        14,
        7,
        24,
        5,
        20,
        1,
        6,
        13,
        3,
        10,
        4,
        19,
        16,
        2,
        15,
        0
    ],
    "solution_status": "success",
    "timed_out_without_tour": false,
    "additional_metadata": {
        "local_search_time": 17.057141415949445,
        "model_inference_time": 0.005491725984029472
    },
    "valid_solution": true,
    "tsp_file": "/home/schafhdaniel@edu.local/tsp-solvers/data/tsp_dataset/25/zurich_25_6.tsp"
}