{
    "timestamp": "20260317_124707",
    "problem": "zurich_100_20",
    "problem_size": 100,
    "type": "TSP",
    "comment": "TSP instance with 100 nodes. City: Zurich, Switzerland, Seed: 62",
    "solver": "concorde",
    "time_to_solve": 0.13583843200467527,
    "cost": 28463.0,
    "tour": [
        0,
        69,
        91,
        96,
        35,
        30,
        7,
        98,
        43,
        19,
        74,
        37,
        6,
        38,
        25,
        14,
        63,
        88,
        93,
        75,
        10,
        34,
        95,
        71,
        47,
        54,
        17,
        20,
        50,
        60,
        67,
        1,
        85,
        84,
        49,
        33,
        68,
        97,
        78,
        4,
        66,
        13,
        18,
        61,
        76,
        5,
        29,
        45,
        39,
        79,
        31,
        86,
        11,
        16,
        2,
        83,
        15,
        23,
        70,
        32,
        80,
        53,
        58,
        82,
        26,
        87,
        56,
        36,
        12,
        9,
        92,
        28,
        99,
        89,
        48,
        22,
        42,
        90,
        8,
        44,
        46,
        62,
        55,
        27,
        40,
        41,
        52,
        64,
        94,
        51,
        3,
        72,
        57,
        24,
        81,
        21,
        73,
        77,
        65,
        59,
        0
    ],
    "solution_status": "Success: Exact solution found. gap is zero",
    "timed_out_without_tour": false,
    "additional_metadata": {
        "lower_bound": 28463.0,
        "upper_bound": 28463.0,
        "gap": 0.0,
        "seed": 42
    },
    "valid_solution": true,
    "tsp_file": "/home/schafhdaniel@edu.local/tsp-solvers/data/tsp_dataset/100/zurich_100_20.tsp"
}