{
    "timestamp": "20260317_234516",
    "problem": "zurich_1000_20",
    "problem_size": 1000,
    "type": "TSP",
    "comment": "TSP instance with 1000 nodes. City: Zurich, Switzerland, Seed: 62",
    "solver": "cuOpt",
    "time_to_solve": 200.10561577393673,
    "cost": 100969.0,
    "tour": [
        0,
        7,
        448,
        569,
        13,
        105,
        317,
        482,
        769,
        415,
        311,
        535,
        744,
        180,
        331,
        444,
        346,
        558,
        767,
        440,
        563,
        95,
        815,
        921,
        294,
        406,
        165,
        644,
        860,
        365,
        465,
        771,
        663,
        236,
        496,
        60,
        594,
        801,
        641,
        619,
        819,
        621,
        720,
        269,
        392,
        19,
        112,
        274,
        399,
        155,
        492,
        800,
        302,
        371,
        579,
        597,
        219,
        14,
        366,
        954,
        782,
        452,
        486,
        783,
        688,
        291,
        197,
        926,
        361,
        807,
        258,
        162,
        930,
        710,
        564,
        225,
        395,
        748,
        426,
        66,
        333,
        267,
        277,
        724,
        40,
        773,
        725,
        141,
        675,
        931,
        152,
        181,
        278,
        645,
        731,
        479,
        139,
        42,
        441,
        956,
        438,
        878,
        685,
        476,
        340,
        80,
        298,
        872,
        830,
        750,
        831,
        648,
        44,
        854,
        62,
        437,
        97,
        977,
        410,
        952,
        351,
        583,
        379,
        398,
        245,
        206,
        466,
        166,
        565,
        690,
        540,
        194,
        702,
        315,
        292,
        48,
        143,
        531,
        560,
        423,
        85,
        297,
        154,
        955,
        850,
        542,
        613,
        596,
        833,
        344,
        789,
        64,
        186,
        290,
        941,
        63,
        660,
        684,
        217,
        33,
        102,
        970,
        167,
        814,
        468,
        550,
        643,
        322,
        996,
        976,
        986,
        994,
        172,
        740,
        887,
        177,
        8,
        708,
        654,
        718,
        736,
        5,
        910,
        907,
        509,
        120,
        806,
        933,
        92,
        324,
        733,
        293,
        780,
        624,
        549,
        905,
        922,
        787,
        873,
        495,
        205,
        93,
        390,
        238,
        890,
        751,
        329,
        730,
        886,
        459,
        626,
        516,
        571,
        857,
        966,
        17,
        454,
        182,
        777,
        73,
        31,
        974,
        742,
        71,
        902,
        960,
        630,
        335,
        281,
        301,
        716,
        589,
        211,
        519,
        768,
        101,
        319,
        268,
        316,
        962,
        207,
        272,
        820,
        78,
        617,
        58,
        939,
        453,
        557,
        67,
        121,
        584,
        463,
        998,
        69,
        45,
        99,
        376,
        383,
        734,
        214,
        822,
        766,
        845,
        858,
        925,
        638,
        233,
        567,
        145,
        793,
        394,
        38,
        667,
        603,
        257,
        661,
        659,
        737,
        184,
        179,
        836,
        554,
        127,
        100,
        533,
        393,
        863,
        113,
        409,
        148,
        380,
        838,
        480,
        802,
        942,
        387,
        790,
        321,
        912,
        990,
        856,
        961,
        107,
        585,
        240,
        314,
        608,
        898,
        520,
        374,
        420,
        757,
        470,
        963,
        464,
        332,
        656,
        349,
        882,
        918,
        665,
        43,
        428,
        588,
        697,
        218,
        128,
        973,
        23,
        983,
        828,
        868,
        553,
        705,
        511,
        160,
        650,
        673,
        713,
        967,
        150,
        869,
        695,
        693,
        578,
        230,
        204,
        256,
        276,
        323,
        296,
        429,
        435,
        227,
        655,
        876,
        867,
        126,
        651,
        752,
        487,
        527,
        455,
        548,
        609,
        266,
        505,
        568,
        370,
        279,
        473,
        627,
        412,
        149,
        270,
        386,
        694,
        190,
        303,
        396,
        372,
        859,
        518,
        997,
        797,
        582,
        950,
        494,
        34,
        714,
        517,
        402,
        385,
        224,
        671,
        574,
        445,
        712,
        760,
        631,
        614,
        795,
        275,
        735,
        286,
        375,
        779,
        252,
        870,
        28,
        541,
        220,
        812,
        35,
        146,
        425,
        794,
        829,
        147,
        811,
        723,
        498,
        27,
        804,
        880,
        696,
        261,
        908,
        984,
        763,
        309,
        776,
        488,
        635,
        416,
        49,
        947,
        77,
        203,
        489,
        260,
        515,
        785,
        81,
        913,
        364,
        502,
        522,
        792,
        888,
        114,
        134,
        841,
        74,
        935,
        354,
        761,
        570,
        948,
        640,
        874,
        504,
        246,
        538,
        843,
        213,
        544,
        510,
        775,
        226,
        3,
        972,
        142,
        610,
        946,
        308,
        478,
        187,
        809,
        342,
        91,
        430,
        719,
        770,
        363,
        239,
        726,
        15,
        348,
        356,
        601,
        709,
        676,
        103,
        22,
        432,
        528,
        209,
        175,
        642,
        889,
        993,
        965,
        526,
        451,
        658,
        662,
        138,
        739,
        914,
        677,
        524,
        11,
        892,
        580,
        525,
        39,
        808,
        657,
        337,
        749,
        446,
        345,
        347,
        212,
        159,
        16,
        26,
        140,
        911,
        24,
        521,
        949,
        485,
        259,
        450,
        144,
        418,
        738,
        471,
        818,
        110,
        765,
        232,
        566,
        339,
        135,
        896,
        537,
        378,
        599,
        824,
        832,
        168,
        431,
        891,
        338,
        721,
        305,
        244,
        957,
        497,
        86,
        283,
        456,
        299,
        433,
        741,
        483,
        561,
        83,
        158,
        116,
        936,
        132,
        988,
        753,
        611,
        904,
        223,
        821,
        503,
        124,
        310,
        36,
        901,
        289,
        893,
        449,
        590,
        543,
        934,
        940,
        208,
        477,
        772,
        699,
        924,
        799,
        9,
        633,
        781,
        87,
        89,
        813,
        618,
        318,
        551,
        328,
        586,
        460,
        129,
        707,
        927,
        355,
        20,
        367,
        1,
        327,
        674,
        151,
        706,
        839,
        958,
        408,
        605,
        680,
        472,
        692,
        18,
        920,
        877,
        75,
        971,
        243,
        943,
        573,
        384,
        501,
        612,
        758,
        587,
        462,
        341,
        668,
        53,
        199,
        336,
        932,
        254,
        871,
        552,
        424,
        604,
        523,
        995,
        137,
        827,
        678,
        108,
        56,
        576,
        215,
        373,
        883,
        547,
        231,
        306,
        88,
        334,
        4,
        978,
        745,
        32,
        54,
        490,
        953,
        897,
        816,
        79,
        242,
        185,
        615,
        192,
        895,
        784,
        989,
        514,
        649,
        562,
        944,
        82,
        798,
        248,
        413,
        778,
        919,
        300,
        104,
        595,
        545,
        417,
        499,
        508,
        133,
        592,
        691,
        411,
        2,
        747,
        47,
        263,
        439,
        805,
        153,
        555,
        980,
        894,
        228,
        909,
        404,
        848,
        539,
        529,
        623,
        840,
        405,
        247,
        157,
        381,
        210,
        377,
        536,
        969,
        556,
        358,
        951,
        629,
        679,
        982,
        115,
        823,
        72,
        434,
        647,
        475,
        46,
        625,
        70,
        937,
        987,
        111,
        131,
        193,
        362,
        352,
        401,
        30,
        851,
        118,
        288,
        722,
        360,
        598,
        689,
        975,
        68,
        864,
        885,
        350,
        622,
        189,
        163,
        382,
        572,
        916,
        178,
        700,
        796,
        493,
        235,
        295,
        125,
        835,
        727,
        664,
        320,
        94,
        264,
        369,
        481,
        701,
        985,
        602,
        76,
        786,
        732,
        273,
        484,
        756,
        353,
        991,
        284,
        325,
        817,
        171,
        852,
        855,
        251,
        513,
        842,
        849,
        762,
        216,
        844,
        117,
        65,
        397,
        229,
        271,
        241,
        900,
        906,
        825,
        928,
        421,
        591,
        136,
        391,
        666,
        183,
        422,
        881,
        945,
        491,
        865,
        467,
        357,
        846,
        803,
        122,
        743,
        156,
        461,
        55,
        51,
        436,
        198,
        57,
        173,
        616,
        170,
        25,
        759,
        698,
        755,
        620,
        837,
        968,
        388,
        442,
        109,
        559,
        84,
        196,
        222,
        530,
        634,
        717,
        50,
        774,
        389,
        21,
        262,
        106,
        447,
        847,
        687,
        711,
        368,
        652,
        862,
        169,
        130,
        788,
        899,
        52,
        443,
        304,
        6,
        191,
        414,
        161,
        607,
        729,
        639,
        672,
        359,
        670,
        307,
        964,
        474,
        61,
        500,
        853,
        929,
        313,
        628,
        326,
        221,
        653,
        981,
        253,
        285,
        546,
        457,
        255,
        10,
        682,
        419,
        123,
        330,
        427,
        458,
        164,
        90,
        728,
        999,
        343,
        715,
        234,
        532,
        98,
        681,
        879,
        265,
        669,
        507,
        195,
        606,
        59,
        810,
        400,
        861,
        12,
        249,
        119,
        992,
        683,
        237,
        202,
        188,
        917,
        791,
        403,
        593,
        96,
        37,
        575,
        646,
        636,
        29,
        884,
        176,
        407,
        686,
        866,
        704,
        201,
        637,
        923,
        632,
        746,
        834,
        41,
        764,
        826,
        506,
        875,
        959,
        577,
        312,
        250,
        754,
        903,
        600,
        979,
        915,
        282,
        703,
        174,
        581,
        938,
        534,
        280,
        469,
        287,
        512,
        200,
        0
    ],
    "solution_status": "success",
    "timed_out_without_tour": false,
    "additional_metadata": {},
    "valid_solution": true,
    "tsp_file": "/home/schafhdaniel@edu.local/tsp-solvers/data/tsp_dataset/1000/zurich_1000_20.tsp"
}