{
    "timestamp": "20260318_002225",
    "problem": "zurich_1000_4",
    "problem_size": 1000,
    "type": "TSP",
    "comment": "TSP instance with 1000 nodes. City: Zurich, Switzerland, Seed: 46",
    "solver": "cuOpt",
    "time_to_solve": 200.31372146005742,
    "cost": 107043.0,
    "tour": [
        0,
        947,
        87,
        330,
        996,
        25,
        983,
        814,
        773,
        863,
        917,
        469,
        302,
        732,
        416,
        346,
        182,
        162,
        935,
        485,
        227,
        219,
        711,
        350,
        231,
        519,
        795,
        327,
        73,
        755,
        168,
        584,
        39,
        943,
        988,
        558,
        381,
        278,
        58,
        303,
        716,
        333,
        883,
        721,
        98,
        284,
        663,
        526,
        828,
        301,
        608,
        516,
        627,
        743,
        298,
        919,
        117,
        556,
        512,
        807,
        903,
        48,
        961,
        295,
        774,
        204,
        598,
        442,
        786,
        541,
        266,
        624,
        926,
        20,
        373,
        70,
        726,
        114,
        459,
        64,
        360,
        157,
        260,
        803,
        968,
        750,
        596,
        898,
        717,
        648,
        471,
        909,
        142,
        367,
        503,
        931,
        31,
        340,
        848,
        736,
        933,
        218,
        691,
        468,
        634,
        123,
        457,
        527,
        546,
        651,
        256,
        465,
        730,
        992,
        849,
        734,
        13,
        893,
        812,
        320,
        252,
        336,
        741,
        6,
        545,
        981,
        40,
        118,
        513,
        925,
        944,
        161,
        372,
        710,
        15,
        604,
        347,
        673,
        657,
        438,
        892,
        801,
        821,
        818,
        498,
        936,
        120,
        470,
        678,
        92,
        852,
        999,
        213,
        27,
        129,
        294,
        408,
        962,
        164,
        406,
        402,
        249,
        592,
        581,
        813,
        400,
        443,
        965,
        283,
        362,
        900,
        616,
        286,
        665,
        701,
        208,
        437,
        349,
        50,
        551,
        756,
        523,
        351,
        122,
        394,
        501,
        765,
        149,
        672,
        747,
        626,
        462,
        61,
        769,
        585,
        479,
        321,
        137,
        620,
        704,
        259,
        577,
        542,
        915,
        687,
        589,
        781,
        951,
        175,
        594,
        904,
        638,
        160,
        110,
        395,
        740,
        310,
        339,
        200,
        870,
        334,
        103,
        370,
        365,
        377,
        376,
        198,
        344,
        18,
        300,
        641,
        681,
        401,
        128,
        779,
        425,
        177,
        582,
        467,
        565,
        784,
        550,
        305,
        412,
        77,
        244,
        536,
        982,
        250,
        844,
        816,
        539,
        54,
        921,
        653,
        525,
        800,
        163,
        554,
        876,
        246,
        957,
        325,
        729,
        978,
        746,
        8,
        222,
        532,
        415,
        712,
        913,
        154,
        100,
        548,
        758,
        530,
        245,
        914,
        647,
        304,
        60,
        440,
        169,
        29,
        885,
        762,
        21,
        216,
        995,
        113,
        439,
        533,
        838,
        661,
        994,
        338,
        528,
        955,
        119,
        713,
        932,
        854,
        599,
        607,
        520,
        858,
        203,
        432,
        7,
        508,
        49,
        436,
        772,
        605,
        662,
        544,
        159,
        973,
        958,
        853,
        89,
        206,
        847,
        472,
        617,
        289,
        531,
        588,
        676,
        189,
        238,
        43,
        287,
        419,
        723,
        410,
        257,
        382,
        731,
        109,
        866,
        635,
        505,
        272,
        771,
        679,
        823,
        879,
        59,
        862,
        127,
        534,
        90,
        326,
        865,
        986,
        980,
        378,
        974,
        41,
        268,
        78,
        225,
        788,
        207,
        918,
        927,
        561,
        221,
        456,
        392,
        859,
        428,
        387,
        407,
        766,
        831,
        696,
        650,
        518,
        811,
        610,
        830,
        580,
        832,
        612,
        47,
        989,
        667,
        487,
        929,
        946,
        547,
        265,
        17,
        985,
        559,
        720,
        698,
        379,
        403,
        590,
        557,
        131,
        288,
        56,
        264,
        455,
        452,
        143,
        515,
        602,
        911,
        96,
        93,
        368,
        937,
        106,
        388,
        430,
        738,
        697,
        700,
        296,
        22,
        808,
        211,
        108,
        664,
        67,
        88,
        796,
        475,
        953,
        671,
        733,
        30,
        141,
        12,
        509,
        652,
        637,
        972,
        748,
        86,
        775,
        522,
        46,
        669,
        560,
        375,
        575,
        80,
        568,
        574,
        799,
        928,
        348,
        845,
        173,
        949,
        724,
        478,
        939,
        279,
        682,
        793,
        171,
        184,
        390,
        181,
        930,
        85,
        464,
        840,
        233,
        998,
        922,
        507,
        640,
        477,
        835,
        660,
        810,
        366,
        385,
        248,
        311,
        587,
        413,
        5,
        483,
        411,
        745,
        463,
        586,
        1,
        230,
        692,
        645,
        719,
        332,
        83,
        622,
        447,
        703,
        383,
        270,
        492,
        764,
        52,
        261,
        882,
        952,
        263,
        101,
        629,
        666,
        144,
        243,
        778,
        631,
        797,
        63,
        619,
        960,
        297,
        751,
        569,
        482,
        674,
        229,
        449,
        908,
        107,
        180,
        824,
        165,
        269,
        642,
        435,
        656,
        907,
        514,
        28,
        887,
        791,
        399,
        426,
        780,
        26,
        654,
        491,
        991,
        537,
        954,
        136,
        916,
        564,
        618,
        441,
        975,
        789,
        842,
        633,
        496,
        636,
        688,
        36,
        591,
        125,
        404,
        461,
        466,
        817,
        328,
        16,
        497,
        488,
        167,
        846,
        728,
        97,
        166,
        535,
        659,
        770,
        19,
        727,
        209,
        827,
        91,
        709,
        240,
        84,
        341,
        583,
        318,
        725,
        34,
        623,
        611,
        923,
        708,
        529,
        783,
        511,
        192,
        345,
        570,
        38,
        555,
        3,
        855,
        809,
        543,
        735,
        868,
        963,
        155,
        185,
        448,
        895,
        495,
        331,
        481,
        102,
        112,
        247,
        135,
        62,
        170,
        195,
        833,
        215,
        644,
        500,
        241,
        147,
        254,
        690,
        888,
        364,
        10,
        140,
        815,
        593,
        23,
        14,
        540,
        55,
        686,
        337,
        906,
        292,
        393,
        549,
        677,
        718,
        418,
        499,
        910,
        353,
        802,
        188,
        872,
        825,
        941,
        267,
        971,
        902,
        323,
        761,
        258,
        324,
        356,
        875,
        130,
        82,
        65,
        132,
        95,
        121,
        787,
        202,
        445,
        655,
        819,
        319,
        856,
        905,
        621,
        776,
        646,
        116,
        178,
        820,
        183,
        397,
        822,
        722,
        864,
        768,
        313,
        643,
        306,
        839,
        354,
        806,
        785,
        934,
        239,
        236,
        2,
        609,
        579,
        715,
        220,
        451,
        737,
        201,
        460,
        794,
        179,
        993,
        389,
        474,
        291,
        417,
        873,
        684,
        134,
        517,
        767,
        851,
        894,
        237,
        956,
        405,
        274,
        881,
        454,
        867,
        890,
        343,
        739,
        945,
        486,
        380,
        74,
        675,
        235,
        281,
        81,
        706,
        275,
        979,
        615,
        115,
        942,
        630,
        37,
        458,
        53,
        493,
        194,
        777,
        150,
        68,
        880,
        190,
        521,
        563,
        552,
        450,
        760,
        886,
        714,
        253,
        290,
        391,
        843,
        940,
        139,
        285,
        891,
        358,
        276,
        57,
        966,
        694,
        433,
        427,
        600,
        976,
        45,
        51,
        837,
        987,
        752,
        352,
        912,
        850,
        658,
        572,
        938,
        566,
        959,
        484,
        689,
        614,
        754,
        76,
        753,
        361,
        228,
        72,
        262,
        153,
        156,
        251,
        282,
        158,
        11,
        314,
        217,
        571,
        232,
        595,
        44,
        506,
        899,
        396,
        309,
        359,
        990,
        307,
        950,
        32,
        494,
        105,
        315,
        744,
        874,
        335,
        836,
        176,
        578,
        857,
        357,
        763,
        502,
        798,
        446,
        9,
        242,
        897,
        567,
        174,
        152,
        151,
        695,
        371,
        625,
        948,
        553,
        901,
        834,
        104,
        639,
        924,
        920,
        597,
        606,
        759,
        172,
        146,
        226,
        510,
        42,
        790,
        997,
        94,
        299,
        420,
        757,
        423,
        342,
        205,
        884,
        685,
        186,
        742,
        322,
        99,
        707,
        670,
        967,
        79,
        69,
        33,
        878,
        699,
        191,
        841,
        111,
        329,
        386,
        826,
        805,
        414,
        473,
        603,
        683,
        576,
        316,
        792,
        369,
        355,
        212,
        124,
        193,
        234,
        970,
        889,
        317,
        424,
        969,
        649,
        829,
        804,
        255,
        145,
        374,
        273,
        312,
        409,
        35,
        453,
        977,
        504,
        224,
        429,
        421,
        877,
        187,
        398,
        199,
        126,
        869,
        480,
        680,
        308,
        66,
        861,
        524,
        444,
        668,
        71,
        538,
        632,
        562,
        693,
        705,
        749,
        75,
        197,
        782,
        964,
        133,
        431,
        214,
        490,
        628,
        896,
        601,
        210,
        363,
        422,
        702,
        4,
        573,
        871,
        138,
        613,
        196,
        280,
        860,
        476,
        148,
        984,
        271,
        489,
        223,
        434,
        24,
        277,
        384,
        293,
        0
    ],
    "solution_status": "success",
    "timed_out_without_tour": false,
    "additional_metadata": {},
    "valid_solution": true,
    "tsp_file": "/home/schafhdaniel@edu.local/tsp-solvers/data/tsp_dataset/1000/zurich_1000_4.tsp"
}